ip_converter.py
version.py
ip2cidr-0.1.0.dist-info/METADATA
ip2cidr-0.1.0.dist-info/WHEEL
ip2cidr-0.1.0.dist-info/entry_points.txt
ip2cidr-0.1.0.dist-info/top_level.txt
ip2cidr-0.1.0.dist-info/RECORD
